LICENSE
MANIFEST.in
README.md
VERSION
setup.py
dirtempl/__init__.py
dirtempl/app.py
dirtempl.egg-info/PKG-INFO
dirtempl.egg-info/SOURCES.txt
dirtempl.egg-info/dependency_links.txt
dirtempl.egg-info/entry_points.txt
dirtempl.egg-info/not-zip-safe
dirtempl.egg-info/requires.txt
dirtempl.egg-info/top_level.txt
hitch/Dockerfile-hitch
hitch/debugrequirements.txt
hitch/docstory.yml
hitch/engine.py
hitch/example-image.png
hitch/hitchreqs.in
hitch/hitchreqs.txt
hitch/key.py
hitch/story/quickstart.story